kobai/__init__.py
kobai/ai_query.py
kobai/ai_rag.py
kobai/databricks_client.py
kobai/demo_tenant_client.py
kobai/genie.py
kobai/ms_authenticate.py
kobai/spark_client.py
kobai/tenant_api.py
kobai/tenant_client.py
kobai_sdk-0.3.3.dist-info/licenses/LICENSE
kobai_sdk-0.3.3.dist-info/METADATA
kobai_sdk-0.3.3.dist-info/WHEEL
kobai_sdk-0.3.3.dist-info/top_level.txt
kobai_sdk-0.3.3.dist-info/RECORD
