Metadata-Version: 2.4
Name: kobai-sdk
Version: 0.3.3
Summary: A package that enables interaction with a Kobai tenant.
Author-email: Ryan Oattes <ryan@kobai.io>
License:                                  Apache License
Project-URL: Homepage, https://kobai.io
Keywords: kobai,databricks,notebook,genie
Classifier: Development Status :: 3 - Alpha
Classifier: Intended Audience :: Developers
Classifier: License :: OSI Approved :: Apache Software License
Classifier: Programming Language :: Python
Classifier: Programming Language :: Python :: 3
Requires-Python: >=3.11
License-File: LICENSE
Requires-Dist: pyspark
Requires-Dist: requests
Requires-Dist: urllib3
Requires-Dist: azure-identity
Requires-Dist: azure-storage-blob
Requires-Dist: langchain-core
Requires-Dist: langchain-community
Requires-Dist: langchain_openai
Requires-Dist: databricks_langchain
Provides-Extra: dev
Requires-Dist: black; extra == "dev"
Requires-Dist: bumpver; extra == "dev"
Requires-Dist: isort; extra == "dev"
Requires-Dist: pip-tools; extra == "dev"
Requires-Dist: pytest; extra == "dev"
Dynamic: license-file
